AUTHORS.rst
LICENSE
MANIFEST.in
README.rst
setup.cfg
setup.py
docs/Makefile
docs/authors.rst
docs/conf.py
docs/contributing.rst
docs/history.rst
docs/index.rst
docs/installation.rst
docs/make.bat
docs/readme.rst
docs/usage.rst
renodiff/__init__.py
renodiff/cli.py
renodiff/renodiff.py
renodiff.egg-info/PKG-INFO
renodiff.egg-info/SOURCES.txt
renodiff.egg-info/dependency_links.txt
renodiff.egg-info/entry_points.txt
renodiff.egg-info/not-zip-safe
renodiff.egg-info/requires.txt
renodiff.egg-info/top_level.txt
tests/__init__.py
tests/test_renodiff.py