Metadata-Version: 1.1
Name: renodiff
Version: 0.1.0
Summary: Convert git patches to reno release notes
Home-page: https://github.com/honza/renodiff
Author: Honza Pokorny
Author-email: me@honza.ca
License: GNU General Public License v3
Keywords: renodiff
Platform: UNKNOWN
Classifier: Development Status :: 2 - Pre-Alpha
Classifier: Intended Audience :: Developers
Classifier: License :: OSI Approved :: GNU General Public License v3 (GPLv3)
Classifier: Natural Language :: English
Classifier: Programming Language :: Python :: 2
Classifier: Programming Language :: Python :: 2.6
Classifier: Programming Language :: Python :: 2.7
Classifier: Programming Language :: Python :: 3
Classifier: Programming Language :: Python :: 3.3
Classifier: Programming Language :: Python :: 3.4
Classifier: Programming Language :: Python :: 3.5
